[

	{
		"name": "Camp Followers",
		"unitType": "Civilian",
		"movement":2,
		"hurryCostModifier": 10,
		"requiredTech": "Economics",
		"obsoleteTech": "Railroads",
		"uniques": ["Can build [Fort] improvements on tiles","Heal adjacent units for an additional 15 HP per turn"],
		"cost": 130
	},
	{
		"name": "Supplies",
		"unitType": "Civilian",
		"movement":3,
		"hurryCostModifier": 10,
		"requiredTech": "Railroads",
		"uniques": ["Heal adjacent units for an additional 15 HP per turn","Can build [Fort] improvements on tiles","Ignores terrain cost"],
		"cost": 200
	}
]
